{
  "name": "nextjs-vercel",
  "id": "nextjs-vercel",
  "description": "Modern documentation with Next.js and Vercel deployment",
  "framework": "nextjs",
  "packageManagers": ["npm", "yarn", "pnpm", "bun"],
  "features": [
    "Next.js 16",
    "React 19",
    "TypeScript",
    "Tailwind CSS",
    "MDX Support",
    "Dark Mode",
    "Search (Algolia)",
    "Responsive Design"
  ],
  "author": "wildan.nrs",
  "repository": "https://github.com/DocuBook/packages/template/nextjs-vercel",
  "homepage": "https://docubook.pro"
}
